pyceo/__init__.py
pyceo/help_mixin.py
pyceo/helpers.py
pyceo/main.py
pyceo/parser.py
pyceo/pastel/__init__.py
pyceo/pastel/pastel.py
pyceo/pastel/stack.py
pyceo/pastel/style.py
pyceo-4.2.1.dist-info/METADATA
pyceo-4.2.1.dist-info/MIT-LICENSE
pyceo-4.2.1.dist-info/WHEEL
pyceo-4.2.1.dist-info/top_level.txt
pyceo-4.2.1.dist-info/RECORD
