Metadata-Version: 2.1
Name: pyceo
Version: 4.2.1
Summary: A minimal and ridiculously good looking command-line-interface toolkit.
Home-page: https://github.com/jpsca/pyceo
Author: Juan-Pablo Scaletti
Author-email: juanpablo@jpscaletti.com
License: MIT
Project-URL: Issue tracker, https://github.com/jpsca/pyceo/issues
Platform: UNKNOWN
Classifier: Development Status :: 5 - Production/Stable
Classifier: Intended Audience :: Developers
Requires-Python: <4.0,>=3.6
Provides-Extra: dev
Requires-Dist: pre-commit ; extra == 'dev'
Requires-Dist: tox ; extra == 'dev'
Provides-Extra: test
Requires-Dist: flake8 ; extra == 'test'
Requires-Dist: flake8-bugbear ; extra == 'test'
Requires-Dist: flake8-import-order ; extra == 'test'
Requires-Dist: flake8-logging-format ; extra == 'test'
Requires-Dist: flake8-quotes ; extra == 'test'
Requires-Dist: pytest ; extra == 'test'
Requires-Dist: pytest-cov ; extra == 'test'
